Workbook

Sheet RAW_DATA
A1: Order_ID | B1: Order_Date | C1: Customer_Name | D1: Customer_Email | E1: Country | F1: Category | G1: Product | H1: Channel | I1: Payment_Method | J1: Status | K1: Quantity | L1: Unit_Price | M1: Discount_Rate | N1: Region | O1: Country_Code | P1: Tax_Rate | Q1: Target_Q1 | R1: Gross_Sales | S1: Discount_Amount | T1: Net_Sales | U1: Total_Cost | V1: Profit | W1: Month | X1: Quarter | Y1: Year
A2: ORD-202493810 | B2: 2024-02-27 00:47 | C2: Allison Hill | D2: donaldgarcia@example.net | E2: Vietnam | F2: Fashion | G2: Jeans | H2: Online | I2: Cash | J2: Returned | K2: 2 | L2: 222.21 | M2: 0.2
A3: ORD-202414165 | B3: 2024-01-16 02:13 | C3: Angie Henderson | D3: davisjesse@example.net | E3: Thailand | F3: Beauty | G3: Shampoo | H3: Marketplace | I3: Debit Card | J3: Returned | K3: 4 | L3: 54.41 | M3: 0.2
A4: ORD-202487236 | B4: 2024-05-22 00:48 | C4: Cristian Santos | D4: lrobinson@example.com | E4: Singapore | F4: Sports | G4: Bicycle | H4: Online | I4: Credit Card | J4: Returned | K4: 4 | L4: 427.64 | M4: 0.05
A5: ORD-202422676 | B5: 2024-07-02 11:38 | C5: Abigail Shaffer | D5: jpeterson@example.org | E5: Vietnam | F5: Electronics | G5: Headphone | H5: Distributor | I5: Cash | J5: Cancelled | K5: 7 | L5: 811.3 | M5: 0
A6: ORD-202485674 | B6: 2024-04-08 22:04 | C6: Gabrielle Davis | D6: howardmaurice@example.com | E6: Indonesia | F6: Fashion | G6: Jacket | H6: Marketplace | I6: E-Wallet | J6: Returned | K6: 4 | L6: 1478.05 | M6: 0
A7: ORD-202493320 | B7: 2024-07-05 05:23 | C7: Monica Herrera | D7: smiller@example.net | E7: Philippines | F7: Fashion | G7: Jacket | H7: Retail Store | I7: Cash | J7: Pending | K7: 2 | L7: 1057.2 | M7: 0.15
A8: ORD-202431417 | B8: 2024-08-24 12:17 | C8: Shannon Ray | D8: williamsjeremy@example.com | E8: Australia | F8: Fashion | G8: Jacket | H8: Online | I8: E-Wallet | J8: Returned | K8: 1 | L8: 1266.64 | M8: 0
A9: ORD-202445093 | B9: 2024-02-03 06:58 | C9: Dr. Sharon James | D9: xreid@example.org | E9: India | F9: Home | G9: Rice Cooker | H9: Marketplace | I9: Debit Card | J9: Cancelled | K9: 7 | L9: 988.33 | M9: 0.2
A10: ORD-202428301 | B10: 2024-05-06 23:35 | C10: Daniel Adams | D10: lynchgeorge@example.net | E10: Australia | F10: Home | G10: Chair | H10: Distributor | I10: Debit Card | J10: Pending | K10: 10 | L10: 651.22 | M10: 0.1
A11: ORD-202476784 | B11: 2024-09-09 02:48 | C11: Joel Nelson | D11: gabriellecameron@example.org | E11: Indonesia | F11: Electronics | G11: Smartphone | H11: Online | I11: Bank Transfer | J11: Returned | K11: 7 | L11: 946.76 | M11: 0.15
A12: ORD-202488104 | B12: 2024-08-27 16:16 | C12: Andrew Stewart | D12: carl95@example.org | E12: Australia | F12: Electronics | G12: Laptop | H12: Distributor | I12: Credit Card | J12: Cancelled | K12: 9 | L12: 1027.34 | M12: 0.05
A13: ORD-202466985 | B13: 2024-03-21 14:00 | C13: Jennifer Rocha | D13: ithomas@example.org | E13: Vietnam | F13: Beauty | G13: Perfume | H13: Distributor | I13: Cash | J13: Pending | K13: 2 | L13: 768.91 | M13: 0.2
... A1001: ORD-202487798 | B1001: 2024-10-30 11:43 | C1001: William Green | D1001: hamiltonandrew@example.com | E1001: South Korea | F1001: Sports | G1001: Bicycle | H1001: Distributor | I1001: Credit Card | J1001: Pending | K1001: 9 | L1001: 666.3 | M1001: 0.2

Sheet REF_Country
A1: Country | B1: Region | C1: Country_Code | D1: Tax_Rate
A2: Indonesia | B2: Southeast Asia | C2: ID | D2: 0.11
A3: Malaysia | B3: Southeast Asia | C3: MY | D3: 0.06
A4: Singapore | B4: Southeast Asia | C4: SG | D4: 0.07
A5: Thailand | B5: Southeast Asia | C5: TH | D5: 0.07
A6: Vietnam | B6: Southeast Asia | C6: VN | D6: 0.1
A7: Philippines | B7: Southeast Asia | C7: PH | D7: 0.12
A8: Japan | B8: East Asia | C8: JP | D8: 0.1
A9: South Korea | B9: East Asia | C9: KR | D9: 0.1
A10: Australia | B10: Oceania | C10: AU | D10: 0.1
A11: India | B11: South Asia | C11: IN | D11: 0.18

Sheet REF_Target
A1: Category | B1: Q1_Target | C1: Q2_Target | D1: Q3_Target | E1: Q4_Target
A2: Electronics | B2: 50000 | C2: 55000 | D2: 60000 | E2: 70000
A3: Fashion | B3: 40000 | C3: 42000 | D3: 45000 | E3: 50000
A4: Home | B4: 30000 | C4: 32000 | D4: 34000 | E4: 38000
A5: Sports | B5: 35000 | C5: 37000 | D5: 39000 | E5: 42000
A6: Beauty | B6: 45000 | C6: 47000 | D6: 49000 | E6: 55000

Sheet REF_Cost
A1: Category | B1: Cost_Per_Unit
A2: Electronics | B2: 450
A3: Fashion | B3: 120
A4: Home | B4: 200
A5: Sports | B5: 150
A6: Beauty | B6: 80

Sheet PETUNJUK
A1: LANGKAH
A2: 1. Sheet RAW_DATA = data mentah (kolom kosong diisi pakai rumus)
A3: 2. REF_Country → sumber VLOOKUP (Region, Country_Code, Tax_Rate)
A4: 3. REF_Target → sumber HLOOKUP (Target Q1-Q4)
A5: 4. REF_Cost → sumber VLOOKUP buat Total_Cost
A6: 5. Buat sheet ANALYSIS + PIVOT
A7: 6. Kerjakan task di dokumen instruksi

Sheet ANALYSIS
A1: Order_ID | B1: Order_Date | C1: Customer_Name | D1: Customer_Email | E1: Country | F1: Category | G1: Product | H1: Channel | I1: Payment_Method | J1: Status | K1: Quantity | L1: Unit_Price | M1: Discount_Rate | N1: Region | O1: Country_Code | P1: Tax_Rate | Q1: Target_Q1 | R1: Gross_Sales | S1: Discount_Amount | T1: Net_Sales | U1: Total_Cost | V1: Profit | W1: Month | X1: Quarter | Y1: Year
A2: ORD-202493810 | B2: 2024-02-27 00:47 | C2: Allison Hill | D2: donaldgarcia@example.net | E2: Vietnam | F2: Fashion | G2: Jeans | H2: Online | I2: Cash | J2: Returned | K2: 2 | L2: 222.21 | M2: 0.2 | N2: =VLOOKUP(Table1[[#This Row],[Country]],REF_Country!$A$1:$D$11,2,FALSE) -> Southeast Asia | O2: =VLOOKUP(Table1[[#This Row],[Country]],REF_Country!$A$1:$D$11,3,FALSE) -> VN | P2: =VLOOKUP(Table1[[#This Row],[Country]],REF_Country!$A$1:$D$11,4,FALSE) -> 0.1 | Q2: =VLOOKUP(Table1[[#This Row],[Category]],REF_Target!$A$1:$E$6,2,FALSE) -> 40000 | R2: =Table1[[#This Row],[Quantity]]*Table1[[#This Row],[Unit_Price]] -> 444.42 | S2: =Table1[[#This Row],[Gross_Sales]]*Table1[[#This Row],[Discount_Rate]] -> 88.884 | T2: =Table1[[#This Row],[Gross_Sales]]-Table1[[#This Row],[Discount_Amount]] -> 355.536 | U2: =VLOOKUP(Table1[[#This Row],[Category]],REF_Cost!$A$1:$B$6,2,FALSE)*Table1[[#This Row],[Quantity]] -> 240 | V2: =Table1[[#This Row],[Net_Sales]]-Table1[[#This Row],[Total_Cost]] -> 115.536 | W2: =TEXT(Table1[[#This Row],[Order_Date]],"mmm") -> Feb | X2: =ROUNDUP(MONTH(Table1[[#This Row],[Order_Date]])/3,0) -> 1 | Y2: =YEAR(Table1[[#This Row],[Order_Date]]) -> 2024
A3: ORD-202414165 | B3: 2024-01-16 02:13 | C3: Angie Henderson | D3: davisjesse@example.net | E3: Thailand | F3: Beauty | G3: Shampoo | H3: Marketplace | I3: Debit Card | J3: Returned | K3: 4 | L3: 54.41 | M3: 0.2 | N3: =VLOOKUP(Table1[[#This Row],[Country]],REF_Country!$A$1:$D$11,2,FALSE) -> Southeast Asia | O3: =VLOOKUP(Table1[[#This Row],[Country]],REF_Country!$A$1:$D$11,3,FALSE) -> TH | P3: =VLOOKUP(Table1[[#This Row],[Country]],REF_Country!$A$1:$D$11,4,FALSE) -> 0.07 | Q3: =VLOOKUP(Table1[[#This Row],[Category]],REF_Target!$A$1:$E$6,2,FALSE) -> 45000 | R3: =Table1[[#This Row],[Quantity]]*Table1[[#This Row],[Unit_Price]] -> 217.64 | S3: =Table1[[#This Row],[Gross_Sales]]*Table1[[#This Row],[Discount_Rate]] -> 43.528 | T3: =Table1[[#This Row],[Gross_Sales]]-Table1[[#This Row],[Discount_Amount]] -> 174.112 | U3: =VLOOKUP(Table1[[#This Row],[Category]],REF_Cost!$A$1:$B$6,2,FALSE)*Table1[[#This Row],[Quantity]] -> 320 | V3: =Table1[[#This Row],[Net_Sales]]-Table1[[#This Row],[Total_Cost]] -> -145.888 | W3: =TEXT(Table1[[#This Row],[Order_Date]],"mmm") -> Jan | X3: =ROUNDUP(MONTH(Table1[[#This Row],[Order_Date]])/3,0) -> 1 | Y3: =YEAR(Table1[[#This Row],[Order_Date]]) -> 2024
A4: ORD-202487236 | B4: 2024-05-22 00:48 | C4: Cristian Santos | D4: lrobinson@example.com | E4: Singapore | F4: Sports | G4: Bicycle | H4: Online | I4: Credit Card | J4: Returned | K4: 4 | L4: 427.64 | M4: 0.05 | N4: =VLOOKUP(Table1[[#This Row],[Country]],REF_Country!$A$1:$D$11,2,FALSE) -> Southeast Asia | O4: =VLOOKUP(Table1[[#This Row],[Country]],REF_Country!$A$1:$D$11,3,FALSE) -> SG | P4: =VLOOKUP(Table1[[#This Row],[Country]],REF_Country!$A$1:$D$11,4,FALSE) -> 0.07 | Q4: =VLOOKUP(Table1[[#This Row],[Category]],REF_Target!$A$1:$E$6,2,FALSE) -> 35000 | R4: =Table1[[#This Row],[Quantity]]*Table1[[#This Row],[Unit_Price]] -> 1710.56 | S4: =Table1[[#This Row],[Gross_Sales]]*Table1[[#This Row],[Discount_Rate]] -> 85.528 | T4: =Table1[[#This Row],[Gross_Sales]]-Table1[[#This Row],[Discount_Amount]] -> 1625.032 | U4: =VLOOKUP(Table1[[#This Row],[Category]],REF_Cost!$A$1:$B$6,2,FALSE)*Table1[[#This Row],[Quantity]] -> 600 | V4: =Table1[[#This Row],[Net_Sales]]-Table1[[#This Row],[Total_Cost]] -> 1025.032 | W4: =TEXT(Table1[[#This Row],[Order_Date]],"mmm") -> May | X4: =ROUNDUP(MONTH(Table1[[#This Row],[Order_Date]])/3,0) -> 2 | Y4: =YEAR(Table1[[#This Row],[Order_Date]]) -> 2024
A5: ORD-202422676 | B5: 2024-07-02 11:38 | C5: Abigail Shaffer | D5: jpeterson@example.org | E5: Vietnam | F5: Electronics | G5: Headphone | H5: Distributor | I5: Cash | J5: Cancelled | K5: 7 | L5: 811.3 | M5: 0 | N5: =VLOOKUP(Table1[[#This Row],[Country]],REF_Country!$A$1:$D$11,2,FALSE) -> Southeast Asia | O5: =VLOOKUP(Table1[[#This Row],[Country]],REF_Country!$A$1:$D$11,3,FALSE) -> VN | P5: =VLOOKUP(Table1[[#This Row],[Country]],REF_Country!$A$1:$D$11,4,FALSE) -> 0.1 | Q5: =VLOOKUP(Table1[[#This Row],[Category]],REF_Target!$A$1:$E$6,2,FALSE) -> 50000 | R5: =Table1[[#This Row],[Quantity]]*Table1[[#This Row],[Unit_Price]] -> 5679.1 | S5: =Table1[[#This Row],[Gross_Sales]]*Table1[[#This Row],[Discount_Rate]] -> 0 | T5: =Table1[[#This Row],[Gross_Sales]]-Table1[[#This Row],[Discount_Amount]] -> 5679.1 | U5: =VLOOKUP(Table1[[#This Row],[Category]],REF_Cost!$A$1:$B$6,2,FALSE)*Table1[[#This Row],[Quantity]] -> 3150 | V5: =Table1[[#This Row],[Net_Sales]]-Table1[[#This Row],[Total_Cost]] -> 2529.1 | W5: =TEXT(Table1[[#This Row],[Order_Date]],"mmm") -> Jul | X5: =ROUNDUP(MONTH(Table1[[#This Row],[Order_Date]])/3,0) -> 3 | Y5: =YEAR(Table1[[#This Row],[Order_Date]]) -> 2024
A6: ORD-202485674 | B6: 2024-04-08 22:04 | C6: Gabrielle Davis | D6: howardmaurice@example.com | E6: Indonesia | F6: Fashion | G6: Jacket | H6: Marketplace | I6: E-Wallet | J6: Returned | K6: 4 | L6: 1478.05 | M6: 0 | N6: =VLOOKUP(Table1[[#This Row],[Country]],REF_Country!$A$1:$D$11,2,FALSE) -> Southeast Asia | O6: =VLOOKUP(Table1[[#This Row],[Country]],REF_Country!$A$1:$D$11,3,FALSE) -> ID | P6: =VLOOKUP(Table1[[#This Row],[Country]],REF_Country!$A$1:$D$11,4,FALSE) -> 0.11 | Q6: =VLOOKUP(Table1[[#This Row],[Category]],REF_Target!$A$1:$E$6,2,FALSE) -> 40000 | R6: =Table1[[#This Row],[Quantity]]*Table1[[#This Row],[Unit_Price]] -> 5912.2 | S6: =Table1[[#This Row],[Gross_Sales]]*Table1[[#This Row],[Discount_Rate]] -> 0 | T6: =Table1[[#This Row],[Gross_Sales]]-Table1[[#This Row],[Discount_Amount]] -> 5912.2 | U6: =VLOOKUP(Table1[[#This Row],[Category]],REF_Cost!$A$1:$B$6,2,FALSE)*Table1[[#This Row],[Quantity]] -> 480 | V6: =Table1[[#This Row],[Net_Sales]]-Table1[[#This Row],[Total_Cost]] -> 5432.2 | W6: =TEXT(Table1[[#This Row],[Order_Date]],"mmm") -> Apr | X6: =ROUNDUP(MONTH(Table1[[#This Row],[Order_Date]])/3,0) -> 2 | Y6: =YEAR(Table1[[#This Row],[Order_Date]]) -> 2024
A7: ORD-202493320 | B7: 2024-07-05 05:23 | C7: Monica Herrera | D7: smiller@example.net | E7: Philippines | F7: Fashion | G7: Jacket | H7: Retail Store | I7: Cash | J7: Pending | K7: 2 | L7: 1057.2 | M7: 0.15 | N7: =VLOOKUP(Table1[[#This Row],[Country]],REF_Country!$A$1:$D$11,2,FALSE) -> Southeast Asia | O7: =VLOOKUP(Table1[[#This Row],[Country]],REF_Country!$A$1:$D$11,3,FALSE) -> PH | P7: =VLOOKUP(Table1[[#This Row],[Country]],REF_Country!$A$1:$D$11,4,FALSE) -> 0.12 | Q7: =VLOOKUP(Table1[[#This Row],[Category]],REF_Target!$A$1:$E$6,2,FALSE) -> 40000 | R7: =Table1[[#This Row],[Quantity]]*Table1[[#This Row],[Unit_Price]] -> 2114.4 | S7: =Table1[[#This Row],[Gross_Sales]]*Table1[[#This Row],[Discount_Rate]] -> 317.16 | T7: =Table1[[#This Row],[Gross_Sales]]-Table1[[#This Row],[Discount_Amount]] -> 1797.24 | U7: =VLOOKUP(Table1[[#This Row],[Category]],REF_Cost!$A$1:$B$6,2,FALSE)*Table1[[#This Row],[Quantity]] -> 240 | V7: =Table1[[#This Row],[Net_Sales]]-Table1[[#This Row],[Total_Cost]] -> 1557.24 | W7: =TEXT(Table1[[#This Row],[Order_Date]],"mmm") -> Jul | X7: =ROUNDUP(MONTH(Table1[[#This Row],[Order_Date]])/3,0) -> 3 | Y7: =YEAR(Table1[[#This Row],[Order_Date]]) -> 2024
A8: ORD-202431417 | B8: 2024-08-24 12:17 | C8: Shannon Ray | D8: williamsjeremy@example.com | E8: Australia | F8: Fashion | G8: Jacket | H8: Online | I8: E-Wallet | J8: Returned | K8: 1 | L8: 1266.64 | M8: 0 | N8: =VLOOKUP(Table1[[#This Row],[Country]],REF_Country!$A$1:$D$11,2,FALSE) -> Oceania | O8: =VLOOKUP(Table1[[#This Row],[Country]],REF_Country!$A$1:$D$11,3,FALSE) -> AU | P8: =VLOOKUP(Table1[[#This Row],[Country]],REF_Country!$A$1:$D$11,4,FALSE) -> 0.1 | Q8: =VLOOKUP(Table1[[#This Row],[Category]],REF_Target!$A$1:$E$6,2,FALSE) -> 40000 | R8: =Table1[[#This Row],[Quantity]]*Table1[[#This Row],[Unit_Price]] -> 1266.64 | S8: =Table1[[#This Row],[Gross_Sales]]*Table1[[#This Row],[Discount_Rate]] -> 0 | T8: =Table1[[#This Row],[Gross_Sales]]-Table1[[#This Row],[Discount_Amount]] -> 1266.64 | U8: =VLOOKUP(Table1[[#This Row],[Category]],REF_Cost!$A$1:$B$6,2,FALSE)*Table1[[#This Row],[Quantity]] -> 120 | V8: =Table1[[#This Row],[Net_Sales]]-Table1[[#This Row],[Total_Cost]] -> 1146.64 | W8: =TEXT(Table1[[#This Row],[Order_Date]],"mmm") -> Aug | X8: =ROUNDUP(MONTH(Table1[[#This Row],[Order_Date]])/3,0) -> 3 | Y8: =YEAR(Table1[[#This Row],[Order_Date]]) -> 2024
A9: ORD-202445093 | B9: 2024-02-03 06:58 | C9: Dr. Sharon James | D9: xreid@example.org | E9: India | F9: Home | G9: Rice Cooker | H9: Marketplace | I9: Debit Card | J9: Cancelled | K9: 7 | L9: 988.33 | M9: 0.2 | N9: =VLOOKUP(Table1[[#This Row],[Country]],REF_Country!$A$1:$D$11,2,FALSE) -> South Asia | O9: =VLOOKUP(Table1[[#This Row],[Country]],REF_Country!$A$1:$D$11,3,FALSE) -> IN | P9: =VLOOKUP(Table1[[#This Row],[Country]],REF_Country!$A$1:$D$11,4,FALSE) -> 0.18 | Q9: =VLOOKUP(Table1[[#This Row],[Category]],REF_Target!$A$1:$E$6,2,FALSE) -> 30000 | R9: =Table1[[#This Row],[Quantity]]*Table1[[#This Row],[Unit_Price]] -> 6918.31 | S9: =Table1[[#This Row],[Gross_Sales]]*Table1[[#This Row],[Discount_Rate]] -> 1383.662 | T9: =Table1[[#This Row],[Gross_Sales]]-Table1[[#This Row],[Discount_Amount]] -> 5534.648 | U9: =VLOOKUP(Table1[[#This Row],[Category]],REF_Cost!$A$1:$B$6,2,FALSE)*Table1[[#This Row],[Quantity]] -> 1400 | V9: =Table1[[#This Row],[Net_Sales]]-Table1[[#This Row],[Total_Cost]] -> 4134.648 | W9: =TEXT(Table1[[#This Row],[Order_Date]],"mmm") -> Feb | X9: =ROUNDUP(MONTH(Table1[[#This Row],[Order_Date]])/3,0) -> 1 | Y9: =YEAR(Table1[[#This Row],[Order_Date]]) -> 2024
A10: ORD-202428301 | B10: 2024-05-06 23:35 | C10: Daniel Adams | D10: lynchgeorge@example.net | E10: Australia | F10: Home | G10: Chair | H10: Distributor | I10: Debit Card | J10: Pending | K10: 10 | L10: 651.22 | M10: 0.1 | N10: =VLOOKUP(Table1[[#This Row],[Country]],REF_Country!$A$1:$D$11,2,FALSE) -> Oceania | O10: =VLOOKUP(Table1[[#This Row],[Country]],REF_Country!$A$1:$D$11,3,FALSE) -> AU | P10: =VLOOKUP(Table1[[#This Row],[Country]],REF_Country!$A$1:$D$11,4,FALSE) -> 0.1 | Q10: =VLOOKUP(Table1[[#This Row],[Category]],REF_Target!$A$1:$E$6,2,FALSE) -> 30000 | R10: =Table1[[#This Row],[Quantity]]*Table1[[#This Row],[Unit_Price]] -> 6512.2 | S10: =Table1[[#This Row],[Gross_Sales]]*Table1[[#This Row],[Discount_Rate]] -> 651.22 | T10: =Table1[[#This Row],[Gross_Sales]]-Table1[[#This Row],[Discount_Amount]] -> 5860.98 | U10: =VLOOKUP(Table1[[#This Row],[Category]],REF_Cost!$A$1:$B$6,2,FALSE)*Table1[[#This Row],[Quantity]] -> 2000 | V10: =Table1[[#This Row],[Net_Sales]]-Table1[[#This Row],[Total_Cost]] -> 3860.98 | W10: =TEXT(Table1[[#This Row],[Order_Date]],"mmm") -> May | X10: =ROUNDUP(MONTH(Table1[[#This Row],[Order_Date]])/3,0) -> 2 | Y10: =YEAR(Table1[[#This Row],[Order_Date]]) -> 2024
A11: ORD-202476784 | B11: 2024-09-09 02:48 | C11: Joel Nelson | D11: gabriellecameron@example.org | E11: Indonesia | F11: Electronics | G11: Smartphone | H11: Online | I11: Bank Transfer | J11: Returned | K11: 7 | L11: 946.76 | M11: 0.15 | N11: =VLOOKUP(Table1[[#This Row],[Country]],REF_Country!$A$1:$D$11,2,FALSE) -> Southeast Asia | O11: =VLOOKUP(Table1[[#This Row],[Country]],REF_Country!$A$1:$D$11,3,FALSE) -> ID | P11: =VLOOKUP(Table1[[#This Row],[Country]],REF_Country!$A$1:$D$11,4,FALSE) -> 0.11 | Q11: =VLOOKUP(Table1[[#This Row],[Category]],REF_Target!$A$1:$E$6,2,FALSE) -> 50000 | R11: =Table1[[#This Row],[Quantity]]*Table1[[#This Row],[Unit_Price]] -> 6627.32 | S11: =Table1[[#This Row],[Gross_Sales]]*Table1[[#This Row],[Discount_Rate]] -> 994.098 | T11: =Table1[[#This Row],[Gross_Sales]]-Table1[[#This Row],[Discount_Amount]] -> 5633.222 | U11: =VLOOKUP(Table1[[#This Row],[Category]],REF_Cost!$A$1:$B$6,2,FALSE)*Table1[[#This Row],[Quantity]] -> 3150 | V11: =Table1[[#This Row],[Net_Sales]]-Table1[[#This Row],[Total_Cost]] -> 2483.222 | W11: =TEXT(Table1[[#This Row],[Order_Date]],"mmm") -> Sep | X11: =ROUNDUP(MONTH(Table1[[#This Row],[Order_Date]])/3,0) -> 3 | Y11: =YEAR(Table1[[#This Row],[Order_Date]]) -> 2024
A12: ORD-202488104 | B12: 2024-08-27 16:16 | C12: Andrew Stewart | D12: carl95@example.org | E12: Australia | F12: Electronics | G12: Laptop | H12: Distributor | I12: Credit Card | J12: Cancelled | K12: 9 | L12: 1027.34 | M12: 0.05 | N12: =VLOOKUP(Table1[[#This Row],[Country]],REF_Country!$A$1:$D$11,2,FALSE) -> Oceania | O12: =VLOOKUP(Table1[[#This Row],[Country]],REF_Country!$A$1:$D$11,3,FALSE) -> AU | P12: =VLOOKUP(Table1[[#This Row],[Country]],REF_Country!$A$1:$D$11,4,FALSE) -> 0.1 | Q12: =VLOOKUP(Table1[[#This Row],[Category]],REF_Target!$A$1:$E$6,2,FALSE) -> 50000 | R12: =Table1[[#This Row],[Quantity]]*Table1[[#This Row],[Unit_Price]] -> 9246.06 | S12: =Table1[[#This Row],[Gross_Sales]]*Table1[[#This Row],[Discount_Rate]] -> 462.303 | T12: =Table1[[#This Row],[Gross_Sales]]-Table1[[#This Row],[Discount_Amount]] -> 8783.757 | U12: =VLOOKUP(Table1[[#This Row],[Category]],REF_Cost!$A$1:$B$6,2,FALSE)*Table1[[#This Row],[Quantity]] -> 4050 | V12: =Table1[[#This Row],[Net_Sales]]-Table1[[#This Row],[Total_Cost]] -> 4733.757 | W12: =TEXT(Table1[[#This Row],[Order_Date]],"mmm") -> Aug | X12: =ROUNDUP(MONTH(Table1[[#This Row],[Order_Date]])/3,0) -> 3 | Y12: =YEAR(Table1[[#This Row],[Order_Date]]) -> 2024
A13: ORD-202466985 | B13: 2024-03-21 14:00 | C13: Jennifer Rocha | D13: ithomas@example.org | E13: Vietnam | F13: Beauty | G13: Perfume | H13: Distributor | I13: Cash | J13: Pending | K13: 2 | L13: 768.91 | M13: 0.2 | N13: =VLOOKUP(Table1[[#This Row],[Country]],REF_Country!$A$1:$D$11,2,FALSE) -> Southeast Asia | O13: =VLOOKUP(Table1[[#This Row],[Country]],REF_Country!$A$1:$D$11,3,FALSE) -> VN | P13: =VLOOKUP(Table1[[#This Row],[Country]],REF_Country!$A$1:$D$11,4,FALSE) -> 0.1 | Q13: =VLOOKUP(Table1[[#This Row],[Category]],REF_Target!$A$1:$E$6,2,FALSE) -> 45000 | R13: =Table1[[#This Row],[Quantity]]*Table1[[#This Row],[Unit_Price]] -> 1537.82 | S13: =Table1[[#This Row],[Gross_Sales]]*Table1[[#This Row],[Discount_Rate]] -> 307.564 | T13: =Table1[[#This Row],[Gross_Sales]]-Table1[[#This Row],[Discount_Amount]] -> 1230.256 | U13: =VLOOKUP(Table1[[#This Row],[Category]],REF_Cost!$A$1:$B$6,2,FALSE)*Table1[[#This Row],[Quantity]] -> 160 | V13: =Table1[[#This Row],[Net_Sales]]-Table1[[#This Row],[Total_Cost]] -> 1070.256 | W13: =TEXT(Table1[[#This Row],[Order_Date]],"mmm") -> Mar | X13: =ROUNDUP(MONTH(Table1[[#This Row],[Order_Date]])/3,0) -> 1 | Y13: =YEAR(Table1[[#This Row],[Order_Date]]) -> 2024
... A1001: ORD-202487798 | B1001: 2024-10-30 11:43 | C1001: William Green | D1001: hamiltonandrew@example.com | E1001: South Korea | F1001: Sports | G1001: Bicycle | H1001: Distributor | I1001: Credit Card | J1001: Pending | K1001: 9 | L1001: 666.3 | M1001: 0.2 | N1001: =VLOOKUP(Table1[[#This Row],[Country]],REF_Country!$A$1:$D$11,2,FALSE) -> East Asia | O1001: =VLOOKUP(Table1[[#This Row],[Country]],REF_Country!$A$1:$D$11,3,FALSE) -> KR | P1001: =VLOOKUP(Table1[[#This Row],[Country]],REF_Country!$A$1:$D$11,4,FALSE) -> 0.1 | Q1001: =VLOOKUP(Table1[[#This Row],[Category]],REF_Target!$A$1:$E$6,2,FALSE) -> 35000 | R1001: =Table1[[#This Row],[Quantity]]*Table1[[#This Row],[Unit_Price]] -> 5996.7 | S1001: =Table1[[#This Row],[Gross_Sales]]*Table1[[#This Row],[Discount_Rate]] -> 1199.34 | T1001: =Table1[[#This Row],[Gross_Sales]]-Table1[[#This Row],[Discount_Amount]] -> 4797.36 | U1001: =VLOOKUP(Table1[[#This Row],[Category]],REF_Cost!$A$1:$B$6,2,FALSE)*Table1[[#This Row],[Quantity]] -> 1350 | V1001: =Table1[[#This Row],[Net_Sales]]-Table1[[#This Row],[Total_Cost]] -> 3447.36 | W1001: =TEXT(Table1[[#This Row],[Order_Date]],"mmm") -> Oct | X1001: =ROUNDUP(MONTH(Table1[[#This Row],[Order_Date]])/3,0) -> 4 | Y1001: =YEAR(Table1[[#This Row],[Order_Date]]) -> 2024

Sheet Pivot_1
A3: Row Labels | B3: Sum of Net_Sales
A4: Australia | B4: 343314.48
A5: India | B5: 374220.47
A6: Indonesia | B6: 384871.14
A7: Japan | B7: 462404.78
A8: Malaysia | B8: 362018.07
A9: Philippines | B9: 339717.75
A10: Singapore | B10: 303589.78
A11: South Korea | B11: 480979.85
A12: Thailand | B12: 392704.8
A13: Vietnam | B13: 452884.45
A14: Grand Total | B14: 3896705.6

Sheet Pivot_2
A3: Row Labels | B3: Sum of Net_Sales
A4: Jan | B4: 346159.77
A5: Feb | B5: 295062.41
A6: Mar | B6: 320397.63
A7: Apr | B7: 374506.61
A8: May | B8: 313658.78
A9: Jun | B9: 305800.73
A10: Jul | B10: 346638.43
A11: Aug | B11: 330882.54
A12: Sep | B12: 328789.65
A13: Oct | B13: 261367.74
A14: Nov | B14: 338561.64
A15: Dec | B15: 334879.64
A16: Grand Total | B16: 3896705.6

Sheet Pivot_3
A3: Sum of Net_Sales | B3: Column Labels
A4: Row Labels | B4: Distributor | C4: Marketplace | D4: Online | E4: Retail Store | F4: Grand Total
A5: Beauty | B5: 199124.56 | C5: 198298.45 | D5: 238495.01 | E5: 110307.33 | F5: 746225.36
A6: Electronics | B6: 202621.25 | C6: 154935.26 | D6: 230138.01 | E6: 262718.76 | F6: 850413.29
A7: Fashion | B7: 221851.5 | C7: 183327.6 | D7: 167735.88 | E7: 186526.47 | F7: 759441.46
A8: Home | B8: 153175.23 | C8: 245208.95 | D8: 197257.38 | E8: 176861.97 | F8: 772503.51
A9: Sports | B9: 157340.72 | C9: 193380.96 | D9: 213661.51 | E9: 203738.76 | F9: 768121.94
A10: Grand Total | B10: 934113.26 | C10: 975151.23 | D10: 1047287.8 | E10: 940153.29 | F10: 3896705.6

Sheet pivot_4
A3: Row Labels | B3: Sum of Quantity | C3: Sum of Net_Sales
A4: Smartphone | B4: 307 | C4: 248515.58
A5: Chair | B5: 297 | C5: 217453.79
A6: Face Wash | B6: 269 | C6: 194423.67
A7: Headphone | B7: 259 | C7: 186949.69
A8: Lipstick | B8: 274 | C8: 170436.55
A9: Grand Total | B9: 1406 | C9: 1017779.3

Sheet Pivot_5
A3: Row Labels | B3: Sum of Profit | C3: Average of Discount_Rate
A4: East Asia | B4: 675174.63 | C4: 0.078110599
A5: Oceania | B5: 251634.48 | C5: 0.094791667
A6: South Asia | B6: 274660.47 | C6: 0.084895833
A7: Southeast Asia | B7: 1561446 | C7: 0.08857868
A8: Grand Total | B8: 2762915.6 | C8: 0.08655

Sheet Dashboard
B3: Global Retail Performance Dashboard 2024
E6: Net Sales | H6: Profit | K6: Quantity | N6: Orders
E7: 3896705.6 | H7: 2762915.6 | K7: 5574 | N7: 1000
